{"name":"Rgrd","tagline":"A R language package to make easy and fun play with Global Device Repositories","body":"### Welcome to Rgrd package.\r\nThis packages helps you to interact with a Global Devide Repository (GRD).\r\n\r\n### Rgrd Manual\r\nGet introduced to this package using our [Rgrd manual](https://github.com/eReuse/Rgrd/blob/master/Rgrd-manual.pdf)\r\n\r\n### How to install last version of this package\r\nDownload it as a .zip or .tar.gz, decompress it, install on R a file with name Rgrd_1.01.tar.gz \r\n\r\n### How to install a test version of this package\r\nOn R type: `install.packages(\"http://data.ereuse.org/packages/Rgrd_0.01.tar.gz\", repos = NULL, type=\"source\")`   \r\n\r\n### How start with this package\r\nOn R type: \r\n***\r\n`    library(Rgrd)`\r\n`    url     <- \"http://sandbox.ereuse.org/api/devices/\"`\r\n`    data    <- getDevices(url)`\r\n`    result  <- data$result`\r\n\r\n### Authors, support or Contact\r\n@dfranquesa","google":"UA-64370884-1","note":"Don't delete this file! It's used internally to help with page regeneration."}